{
  "timestamp": "2026-04-20T15:07:14.927Z",
  "objects": [
    {
      "category": "person",
      "confidence": 1.0,
      "id": "e3de3545-8373-4147-95c3-1df8616cc97c",
      "type": "person",
      "translation": [
        6.850478892236563,
        6.8968437049437465,
        -1.182779720666336e-27
      ],
      "size": [
        0.24538418886748303,
        0.24538418886748303,
        0.26714776524713346
      ],
      "velocity": [
        0.0762951131841004,
        -0.005801583423830654,
        0.0
      ],
      "rotation": [
        0,
        0,
        0,
        1
      ],
      "metadata": {
        "object_id": {
          "label": "",
          "model_name": ""
        }
      },
      "visibility": [
        "Camera_01"
      ],
      "similarity": null,
      "first_seen": "2026-04-20T15:07:14.836Z",
      "camera_bounds": {
        "Camera_01": {
          "x": 765.0,
          "y": 400.0,
          "width": 100.0,
          "height": 138.0
        }
      }
    },
    {
      "category": "person",
      "confidence": 1.0,
      "id": "ff7d52ef-cb0d-4a88-9df1-758bc7aa776c",
      "type": "person",
      "translation": [
        5.35625873087104,
        7.183459999213547,
        -3.147997380338668e-17
      ],
      "size": [
        0.6413960920348716,
        0.6413960920348716,
        0.8511202958697819
      ],
      "velocity": [
        0.19017612739673745,
        0.5324574842124375,
        0.0
      ],
      "rotation": [
        0,
        0,
        0,
        1
      ],
      "metadata": {
        "object_id": {
          "label": "",
          "model_name": ""
        }
      },
      "visibility": [],
      "similarity": 1.4922587871551514,
      "first_seen": "2026-04-20T15:07:11.013Z",
      "camera_bounds": {}
    }
  ],
  "id": "db68a737-92db-4477-880b-07bc7d658ab9",
  "name": "Office",
  "scene_rate": 8.4,
  "rate": {
    "Camera_02": 3.9558920358481027,
    "Camera_01": 4.233128048163499
  }
}