{
  "timestamp": "2026-04-20T14:54:30.038Z",
  "objects": [
    {
      "category": "person",
      "confidence": 1.0,
      "id": "b7affa99-32e3-4b9a-8edb-548a45d02089",
      "type": "person",
      "translation": [
        2.3668456624265555,
        5.520101887277539,
        0.0
      ],
      "size": [
        0.5225715283131587,
        0.5225715283131587,
        0.38433572948810185
      ],
      "velocity": [
        -0.0025842020270589513,
        0.016469341454406282,
        0.0
      ],
      "rotation": [
        0,
        0,
        0,
        1
      ],
      "metadata": {
        "object_id": {
          "label": "",
          "model_name": ""
        }
      },
      "visibility": [
        "Camera_02"
      ],
      "similarity": null,
      "first_seen": "2026-04-20T14:54:29.571Z",
      "camera_bounds": {
        "Camera_02": {
          "x": 1486.0,
          "y": 501.0,
          "width": 248.0,
          "height": 266.0
        }
      }
    },
    {
      "category": "person",
      "confidence": 1.0,
      "id": "c9e9ec4a-8d84-4332-855d-c93bdef2e0ec",
      "type": "person",
      "translation": [
        2.0785939910348645,
        5.233154975674255,
        0.0
      ],
      "size": [
        0.3115544842020528,
        0.3115544842020528,
        0.2484047190820949
      ],
      "velocity": [
        0.0504906375255874,
        -0.027585489206515098,
        0.0
      ],
      "rotation": [
        0,
        0,
        0,
        1
      ],
      "metadata": {
        "object_id": {
          "label": "",
          "model_name": ""
        }
      },
      "visibility": [
        "Camera_02"
      ],
      "similarity": null,
      "first_seen": "2026-04-20T14:54:24.918Z",
      "camera_bounds": {
        "Camera_02": {
          "x": 1327.0,
          "y": 607.0,
          "width": 148.0,
          "height": 172.0
        }
      }
    },
    {
      "category": "person",
      "confidence": 1.0,
      "id": "42781b98-1d71-42d0-8351-a92baf8a16fd",
      "type": "person",
      "translation": [
        2.6168576951249967,
        3.3333282537190163,
        1.7877415662254337e-24
      ],
      "size": [
        1.079896796728002,
        1.079896796728002,
        0.8984355598812173
      ],
      "velocity": [
        0.30763169241079713,
        0.6147259976399312,
        0.0
      ],
      "rotation": [
        0,
        0,
        0,
        1
      ],
      "metadata": {
        "object_id": {
          "label": "",
          "model_name": ""
        }
      },
      "visibility": [
        "Camera_02"
      ],
      "similarity": 0.0,
      "first_seen": "2026-04-20T14:54:19.098Z",
      "camera_bounds": {
        "Camera_02": {
          "x": 1405.0,
          "y": 456.0,
          "width": 515.0,
          "height": 624.0
        }
      }
    }
  ],
  "id": "db68a737-92db-4477-880b-07bc7d658ab9",
  "name": "Office",
  "scene_rate": 8.5,
  "rate": {
    "Camera_02": 4.052456390645621,
    "Camera_01": 4.378694301340805
  }
}