{
  "timestamp": "2026-04-20T15:51:13.010Z",
  "objects": [
    {
      "category": "person",
      "confidence": 1.0,
      "id": "801f3023-a4db-4c10-94a4-0f95b0470f16",
      "type": "person",
      "translation": [
        6.701911788106406,
        6.503550670013412,
        -1.527780162248081e-23
      ],
      "size": [
        0.2748238113592807,
        0.2748238113592807,
        0.2883829940081604
      ],
      "velocity": [
        -0.01026130624589459,
        -0.021255798309503436,
        0.0
      ],
      "rotation": [
        0,
        0,
        0,
        1
      ],
      "metadata": {
        "object_id": {
          "label": "",
          "model_name": ""
        }
      },
      "visibility": [
        "Camera_01"
      ],
      "similarity": null,
      "first_seen": "2026-04-20T15:51:07.726Z",
      "camera_bounds": {
        "Camera_01": {
          "x": 807.0,
          "y": 382.0,
          "width": 106.0,
          "height": 144.0
        }
      }
    },
    {
      "category": "person",
      "confidence": 1.0,
      "id": "6fe01661-9d8d-474e-966b-e047804dc79c",
      "type": "person",
      "translation": [
        7.009115617770016,
        7.307178764770895,
        0.0
      ],
      "size": [
        0.30795130721882114,
        0.30795130721882114,
        0.32954442574364856
      ],
      "velocity": [
        0.07466634686981612,
        0.19181317748830964,
        0.0
      ],
      "rotation": [
        0,
        0,
        0,
        1
      ],
      "metadata": {
        "object_id": {
          "label": "",
          "model_name": ""
        }
      },
      "visibility": [
        "Camera_01"
      ],
      "similarity": null,
      "first_seen": "2026-04-20T15:51:08.374Z",
      "camera_bounds": {
        "Camera_01": {
          "x": 504.0,
          "y": 324.0,
          "width": 152.0,
          "height": 192.0
        }
      }
    }
  ],
  "id": "db68a737-92db-4477-880b-07bc7d658ab9",
  "name": "Office",
  "scene_rate": 9.0,
  "rate": {
    "Camera_02": 4.471281881807401,
    "Camera_01": 4.734595595171852
  }
}