{
  "timestamp": "2026-04-20T15:06:24.492Z",
  "objects": [
    {
      "category": "person",
      "confidence": 1.0,
      "id": "651281e0-cb63-4059-bb36-c9efca0bb6cb",
      "type": "person",
      "translation": [
        2.4577104323916483,
        5.297308413005352,
        0.0
      ],
      "size": [
        0.36656462159852543,
        0.36656462159852543,
        0.5114351082401355
      ],
      "velocity": [
        3.768891440372185e-15,
        -5.01811375376559e-15,
        0.0
      ],
      "rotation": [
        0,
        0,
        0,
        1
      ],
      "metadata": {
        "object_id": {
          "label": "",
          "model_name": ""
        }
      },
      "visibility": [
        "Camera_02"
      ],
      "similarity": null,
      "first_seen": "2026-04-20T15:06:24.267Z",
      "camera_bounds": {
        "Camera_02": {
          "x": 1588.0,
          "y": 441.0,
          "width": 174.0,
          "height": 354.0
        }
      }
    }
  ],
  "id": "db68a737-92db-4477-880b-07bc7d658ab9",
  "name": "Office",
  "scene_rate": 8.4,
  "rate": {
    "Camera_02": 7.5885578681420345,
    "Camera_01": 3.609440714568562
  }
}