{
  "timestamp": "2026-04-20T14:56:31.001Z",
  "objects": [
    {
      "category": "person",
      "confidence": 1.0,
      "id": "a8d5f36b-bd27-40b8-a9ef-94a6e6c29aab",
      "type": "person",
      "translation": [
        2.36793131494715,
        5.512789698630815,
        0.0
      ],
      "size": [
        0.5225648466725472,
        0.5225648466725472,
        0.38433217485670207
      ],
      "velocity": [
        -0.0024139884387220506,
        0.014582655293687786,
        0.0
      ],
      "rotation": [
        0,
        0,
        0,
        1
      ],
      "metadata": {
        "object_id": {
          "label": "",
          "model_name": ""
        }
      },
      "visibility": [
        "Camera_02"
      ],
      "similarity": null,
      "first_seen": "2026-04-20T14:56:30.789Z",
      "camera_bounds": {
        "Camera_02": {
          "x": 1487.0,
          "y": 502.0,
          "width": 248.0,
          "height": 266.0
        }
      }
    },
    {
      "category": "person",
      "confidence": 1.0,
      "id": "9be2b32a-53b9-4a48-9991-617bf4202fe2",
      "type": "person",
      "translation": [
        2.0331491327807125,
        5.115313217200006,
        0.0
      ],
      "size": [
        0.3115864250909284,
        0.3115864250909284,
        0.2484226612395499
      ],
      "velocity": [
        0.010260584696618447,
        -0.16501365567529858,
        0.0
      ],
      "rotation": [
        0,
        0,
        0,
        1
      ],
      "metadata": {
        "object_id": {
          "label": "",
          "model_name": ""
        }
      },
      "visibility": [
        "Camera_02"
      ],
      "similarity": null,
      "first_seen": "2026-04-20T14:56:30.363Z",
      "camera_bounds": {
        "Camera_02": {
          "x": 1324.0,
          "y": 600.0,
          "width": 148.0,
          "height": 172.0
        }
      }
    },
    {
      "category": "person",
      "confidence": 1.0,
      "id": "3cb8fb0e-9e4f-41e6-b0cb-35f4f14af0a2",
      "type": "person",
      "translation": [
        4.6269510183603835,
        5.054928610809814,
        0.0
      ],
      "size": [
        0.5409179952090133,
        0.5409179952090133,
        0.5277562122722046
      ],
      "velocity": [
        0.02139155235315346,
        0.07049832352676359,
        0.0
      ],
      "rotation": [
        0,
        0,
        0,
        1
      ],
      "metadata": {
        "object_id": {
          "label": "",
          "model_name": ""
        }
      },
      "visibility": [
        "Camera_01"
      ],
      "similarity": 0.8834585547447205,
      "first_seen": "2026-04-20T14:56:23.249Z",
      "camera_bounds": {
        "Camera_01": {
          "x": 1567.0,
          "y": 612.0,
          "width": 168.0,
          "height": 398.0
        }
      }
    },
    {
      "category": "person",
      "confidence": 1.0,
      "id": "42781b98-1d71-42d0-8351-a92baf8a16fd",
      "type": "person",
      "translation": [
        2.3006458878811684,
        2.934468117880611,
        0.0
      ],
      "size": [
        1.1155087898189344,
        1.1155087898189344,
        0.8998473735494477
      ],
      "velocity": [
        0.08489657058111486,
        0.055291876356966065,
        0.0
      ],
      "rotation": [
        0,
        0,
        0,
        1
      ],
      "metadata": {
        "object_id": {
          "label": "",
          "model_name": ""
        }
      },
      "visibility": [
        "Camera_02"
      ],
      "similarity": 0.0,
      "first_seen": "2026-04-20T14:56:22.981Z",
      "camera_bounds": {
        "Camera_02": {
          "x": 1388.0,
          "y": 455.0,
          "width": 532.0,
          "height": 625.0
        }
      }
    }
  ],
  "id": "db68a737-92db-4477-880b-07bc7d658ab9",
  "name": "Office",
  "scene_rate": 7.8,
  "rate": {
    "Camera_02": 4.086416858117228,
    "Camera_01": 4.292603430121517
  }
}