{
  "timestamp": "2026-04-20T15:54:00.561Z",
  "objects": [
    {
      "category": "person",
      "confidence": 1.0,
      "id": "be4c04d5-729d-428c-be22-b4cd9d5c3b55",
      "type": "person",
      "translation": [
        4.979915599196211,
        5.081798546748986,
        0.0
      ],
      "size": [
        0.3931980298546014,
        0.3931980298546014,
        0.5067612849488605
      ],
      "velocity": [
        0.05481092541144894,
        0.07486589700699209,
        0.0
      ],
      "rotation": [
        0,
        0,
        0,
        1
      ],
      "metadata": {
        "object_id": {
          "label": "",
          "model_name": ""
        }
      },
      "visibility": [
        "Camera_01"
      ],
      "similarity": null,
      "first_seen": "2026-04-20T15:53:55.497Z",
      "camera_bounds": {
        "Camera_01": {
          "x": 1494.0,
          "y": 549.0,
          "width": 116.0,
          "height": 336.0
        }
      }
    },
    {
      "category": "person",
      "confidence": 1.0,
      "id": "42781b98-1d71-42d0-8351-a92baf8a16fd",
      "type": "person",
      "translation": [
        2.2363380195704434,
        2.6117742822594536,
        0.0
      ],
      "size": [
        1.3331637320443308,
        1.3331637320443308,
        0.9111386318683079
      ],
      "velocity": [
        0.18231983048511274,
        0.009810866551146175,
        0.0
      ],
      "rotation": [
        0,
        0,
        0,
        1
      ],
      "metadata": {
        "object_id": {
          "label": "",
          "model_name": ""
        }
      },
      "visibility": [
        "Camera_02"
      ],
      "similarity": 0.0,
      "first_seen": "2026-04-20T15:53:52.824Z",
      "camera_bounds": {
        "Camera_02": {
          "x": 1252.0,
          "y": 447.0,
          "width": 636.0,
          "height": 633.0
        }
      }
    }
  ],
  "id": "db68a737-92db-4477-880b-07bc7d658ab9",
  "name": "Office",
  "scene_rate": 8.8,
  "rate": {
    "Camera_02": 4.015712319523562,
    "Camera_01": 4.422603603550737
  }
}