{
  "timestamp": "2026-04-20T15:58:31.156Z",
  "objects": [
    {
      "category": "person",
      "confidence": 1.0,
      "id": "4f00b3ae-a633-44c5-8bfb-73f92ddf11b2",
      "type": "person",
      "translation": [
        6.936133836903587,
        7.115318375183805,
        -8.040027223952203e-17
      ],
      "size": [
        0.32106246057029075,
        0.32106246057029075,
        0.33941238841717253
      ],
      "velocity": [
        0.006561396411997924,
        -0.006382772910159559,
        0.0
      ],
      "rotation": [
        0,
        0,
        0,
        1
      ],
      "metadata": {
        "object_id": {
          "label": "",
          "model_name": ""
        }
      },
      "visibility": [
        "Camera_01"
      ],
      "similarity": null,
      "first_seen": "2026-04-20T15:58:25.800Z",
      "camera_bounds": {
        "Camera_01": {
          "x": 548.0,
          "y": 320.0,
          "width": 152.0,
          "height": 192.0
        }
      }
    },
    {
      "category": "person",
      "confidence": 1.0,
      "id": "ff7d52ef-cb0d-4a88-9df1-758bc7aa776c",
      "type": "person",
      "translation": [
        7.608340039273861,
        7.873796806629373,
        -2.063023831954899e-19
      ],
      "size": [
        0.14228379642181377,
        0.14228379642181377,
        0.19232187442557325
      ],
      "velocity": [
        0.2534724930350715,
        0.01599165377287544,
        0.0
      ],
      "rotation": [
        0,
        0,
        0,
        1
      ],
      "metadata": {
        "object_id": {
          "label": "",
          "model_name": ""
        }
      },
      "visibility": [
        "Camera_01"
      ],
      "similarity": 0.0,
      "first_seen": "2026-04-20T15:58:21.692Z",
      "camera_bounds": {
        "Camera_01": {
          "x": 50.0,
          "y": 294.0,
          "width": 98.0,
          "height": 136.0
        }
      }
    }
  ],
  "id": "db68a737-92db-4477-880b-07bc7d658ab9",
  "name": "Office",
  "scene_rate": 9.7,
  "rate": {
    "Camera_02": 4.88855599236602,
    "Camera_01": 4.765050201673108
  }
}