{
  "timestamp": "2026-04-20T14:53:05.526Z",
  "objects": [
    {
      "category": "person",
      "confidence": 1.0,
      "id": "366b322c-d1bf-48f3-aa5f-bc5ea2048014",
      "type": "person",
      "translation": [
        2.495764496313049,
        5.400886921161044,
        0.0
      ],
      "size": [
        0.1812505449457662,
        0.1812505449457662,
        0.27168862531981497
      ],
      "velocity": [
        0.014690463117773007,
        0.16413495616650373,
        0.0
      ],
      "rotation": [
        0,
        0,
        0,
        1
      ],
      "metadata": {
        "object_id": {
          "label": "",
          "model_name": ""
        }
      },
      "visibility": [
        "Camera_02"
      ],
      "similarity": null,
      "first_seen": "2026-04-20T14:53:03.590Z",
      "camera_bounds": {
        "Camera_02": {
          "x": 1669.0,
          "y": 590.0,
          "width": 86.0,
          "height": 188.0
        }
      }
    },
    {
      "category": "person",
      "confidence": 1.0,
      "id": "ffe15c9c-44d0-449e-bc3d-b55c629529ff",
      "type": "person",
      "translation": [
        6.5730393148513455,
        7.081241064246308,
        1.6623656626458092e-18
      ],
      "size": [
        0.21543409412104886,
        0.21543409412104886,
        0.23971851500206437
      ],
      "velocity": [
        -0.001633136723673833,
        -0.01308953526100843,
        0.0
      ],
      "rotation": [
        0,
        0,
        0,
        1
      ],
      "metadata": {
        "object_id": {
          "label": "",
          "model_name": ""
        }
      },
      "visibility": [
        "Camera_01"
      ],
      "similarity": null,
      "first_seen": "2026-04-20T14:53:04.608Z",
      "camera_bounds": {
        "Camera_01": {
          "x": 639.0,
          "y": 485.0,
          "width": 106.0,
          "height": 146.0
        }
      }
    },
    {
      "category": "person",
      "confidence": 1.0,
      "id": "53c912a0-aed6-4349-8152-af74c85cd62b",
      "type": "person",
      "translation": [
        0.3252311566687818,
        1.5030456249008184,
        0.0
      ],
      "size": [
        1.1771539997419287,
        1.1771539997419287,
        1.1406507727583608
      ],
      "velocity": [
        -0.43389451147903674,
        -0.18757395823353695,
        0.0
      ],
      "rotation": [
        0,
        0,
        0,
        1
      ],
      "metadata": {
        "object_id": {
          "label": "",
          "model_name": ""
        }
      },
      "visibility": [
        "Camera_02"
      ],
      "similarity": null,
      "first_seen": "2026-04-20T14:52:59.158Z",
      "camera_bounds": {
        "Camera_02": {
          "x": 0.0,
          "y": 258.0,
          "width": 564.0,
          "height": 794.0
        }
      }
    },
    {
      "category": "person",
      "confidence": 1.0,
      "id": "a7624580-cecc-4d47-9480-bb093d320cd7",
      "type": "person",
      "translation": [
        7.114990466865963,
        8.455618514291928,
        -6.97484862081725e-18
      ],
      "size": [
        0.30327448131490975,
        0.30327448131490975,
        0.2761330829589648
      ],
      "velocity": [
        0.3055597124484862,
        0.2561030195905302,
        0.0
      ],
      "rotation": [
        0,
        0,
        0,
        1
      ],
      "metadata": {
        "object_id": {
          "label": "",
          "model_name": ""
        }
      },
      "visibility": [
        "Camera_01"
      ],
      "similarity": 0.0,
      "first_seen": "2026-04-20T14:52:55.349Z",
      "camera_bounds": {
        "Camera_01": {
          "x": 46.0,
          "y": 407.0,
          "width": 222.0,
          "height": 228.0
        }
      }
    }
  ],
  "id": "db68a737-92db-4477-880b-07bc7d658ab9",
  "name": "Office",
  "scene_rate": 8.6,
  "rate": {
    "Camera_02": 3.941895956709843,
    "Camera_01": 4.0734138317302016
  }
}