{
  "id": "Camera_01",
  "debug_mac": "b5:c7:7b:3f:4c:a8",
  "timestamp": "2026-04-20T15:04:54.220Z",
  "debug_timestamp_end": "2026-04-20T15:04:54.241Z",
  "debug_processing_time": 0.021319150924682617,
  "rate": 4.778682491822788,
  "objects": {
    "person": [
      {
        "category": "person",
        "confidence": 1.0,
        "bounding_box_px": {
          "x": 1459,
          "y": 491,
          "width": 122,
          "height": 362
        },
        "metadata": {
          "object_id": {
            "label": "",
            "model_name": ""
          }
        },
        "id": 1
      }
    ]
  }
}